mplbezier.py
mplbezier-0.1.0.dist-info/METADATA
mplbezier-0.1.0.dist-info/WHEEL
mplbezier-0.1.0.dist-info/top_level.txt
mplbezier-0.1.0.dist-info/RECORD
