Metadata-Version: 2.2
Name: mplbezier
Version: 0.1.0
Summary: Draw Bezier curves on your matplotlib plots interactively.
Author-email: Frederic Schell <frederic.schell@iws.fraunhofer.de>
License: MIT
Requires-Dist: matplotlib
